sphinx_affiliates/__init__.py
sphinx_affiliates/searchtools.js
sphinx_affiliates-0.2.1.dist-info/LICENSE
sphinx_affiliates-0.2.1.dist-info/METADATA
sphinx_affiliates-0.2.1.dist-info/WHEEL
sphinx_affiliates-0.2.1.dist-info/top_level.txt
sphinx_affiliates-0.2.1.dist-info/RECORD
