Metadata-Version: 2.1
Name: sphinx-affiliates
Version: 0.2.1
Summary: Tools for integrating affiliated Sphinx sites
Home-page: https://github.com/mattip/sphinx-affiliates
Author: mattip
Author-email: mattigit@picus.org.il
License: MIT
Platform: UNKNOWN
Classifier: Development Status :: 4 - Beta
Classifier: Environment :: Plugins
Classifier: Environment :: Web Environment
Classifier: Framework :: Sphinx :: Extension
Classifier: Intended Audience :: Developers
Classifier: License :: OSI Approved :: MIT License
Classifier: Natural Language :: English
Classifier: Operating System :: OS Independent
Classifier: Programming Language :: Python :: 2.7
Classifier: Programming Language :: Python :: 3.6
Classifier: Programming Language :: Python :: 3.7
Classifier: Programming Language :: Python :: 3.8
Classifier: Programming Language :: Python
Classifier: Topic :: Documentation :: Sphinx
Requires-Python: >=2.7
Requires-Dist: sphinx (<4,>=1.8.5)
Provides-Extra: code_style
Requires-Dist: pre-commit (==2.6) ; extra == 'code_style'
Provides-Extra: testing
Requires-Dist: coverage ; extra == 'testing'
Requires-Dist: pytest ; extra == 'testing'
Requires-Dist: pytest-cov ; extra == 'testing'
Requires-Dist: sphinx-testing ; extra == 'testing'
